CHANGES.txt
LICENSE.txt
MANIFEST.in
README.rst
setup.py
js/__init__.py
js.select2.egg-info/PKG-INFO
js.select2.egg-info/SOURCES.txt
js.select2.egg-info/dependency_links.txt
js.select2.egg-info/entry_points.txt
js.select2.egg-info/namespace_packages.txt
js.select2.egg-info/not-zip-safe
js.select2.egg-info/requires.txt
js.select2.egg-info/top_level.txt
js/select2/__init__.py
js/select2/test_select2.js.txt
js/select2/resources/css/select2.css
js/select2/resources/css/select2.min.css
js/select2/resources/js/select2.full.js
js/select2/resources/js/select2.full.min.js
js/select2/resources/js/select2.js
js/select2/resources/js/select2.min.js
js/select2/resources/js/i18n/ar.js
js/select2/resources/js/i18n/az.js
js/select2/resources/js/i18n/bg.js
js/select2/resources/js/i18n/ca.js
js/select2/resources/js/i18n/cs.js
js/select2/resources/js/i18n/da.js
js/select2/resources/js/i18n/de.js
js/select2/resources/js/i18n/el.js
js/select2/resources/js/i18n/en.js
js/select2/resources/js/i18n/es.js
js/select2/resources/js/i18n/et.js
js/select2/resources/js/i18n/eu.js
js/select2/resources/js/i18n/fa.js
js/select2/resources/js/i18n/fi.js
js/select2/resources/js/i18n/fr.js
js/select2/resources/js/i18n/gl.js
js/select2/resources/js/i18n/he.js
js/select2/resources/js/i18n/hi.js
js/select2/resources/js/i18n/hr.js
js/select2/resources/js/i18n/hu.js
js/select2/resources/js/i18n/hy.js
js/select2/resources/js/i18n/id.js
js/select2/resources/js/i18n/is.js
js/select2/resources/js/i18n/it.js
js/select2/resources/js/i18n/ja.js
js/select2/resources/js/i18n/km.js
js/select2/resources/js/i18n/ko.js
js/select2/resources/js/i18n/lt.js
js/select2/resources/js/i18n/lv.js
js/select2/resources/js/i18n/mk.js
js/select2/resources/js/i18n/ms.js
js/select2/resources/js/i18n/nb.js
js/select2/resources/js/i18n/nl.js
js/select2/resources/js/i18n/pl.js
js/select2/resources/js/i18n/pt-BR.js
js/select2/resources/js/i18n/pt.js
js/select2/resources/js/i18n/ro.js
js/select2/resources/js/i18n/ru.js
js/select2/resources/js/i18n/sk.js
js/select2/resources/js/i18n/sl.js
js/select2/resources/js/i18n/sr-Cyrl.js
js/select2/resources/js/i18n/sr.js
js/select2/resources/js/i18n/sv.js
js/select2/resources/js/i18n/th.js
js/select2/resources/js/i18n/tr.js
js/select2/resources/js/i18n/uk.js
