Metadata-Version: 1.0
Name: js.select2
Version: 4.0.4.post1
Summary: Fanstatic packaging of select2
Home-page: https://github.com/delijati/js.select2
Author: Josip Delic
Author-email: delijati@delijati.net
License: BSD
Platform: UNKNOWN
